hashquery/__init__.py
hashquery/demo/__init__.py
hashquery/demo/project.py
hashquery/integration/__init__.py
hashquery/integration/hashboard/__init__.py
hashquery/integration/hashboard/api.py
hashquery/integration/hashboard/base_uri.py
hashquery/integration/hashboard/credentials.py
hashquery/integration/hashboard/hashboard_project.py
hashquery/integration/hashboard/project_import.py
hashquery/model/__init__.py
hashquery/model/accessors.py
hashquery/model/activity_schema.py
hashquery/model/column.py
hashquery/model/model.py
hashquery/model/namespace.py
hashquery/model/column_expression/__init__.py
hashquery/model/column_expression/binary_op.py
hashquery/model/column_expression/cases.py
hashquery/model/column_expression/column_expression.py
hashquery/model/column_expression/column_name.py
hashquery/model/column_expression/format_timestamp.py
hashquery/model/column_expression/granularity.py
hashquery/model/column_expression/py_value.py
hashquery/model/column_expression/sql_function.py
hashquery/model/column_expression/sql_text.py
hashquery/model/column_expression/subquery_expression.py
hashquery/model/connection/__init__.py
hashquery/model/connection/bigquery_connection.py
hashquery/model/connection/connection.py
hashquery/model/connection/duckdb_connection.py
hashquery/model/connection/hashboard_data_connection.py
hashquery/model/func/__init__.py
hashquery/model/func/_cases.py
hashquery/model/func/_logical.py
hashquery/model/func/_sql_functions.py
hashquery/model/func/_temporal.py
hashquery/model/source/__init__.py
hashquery/model/source/aggregate.py
hashquery/model/source/filter.py
hashquery/model/source/join_one.py
hashquery/model/source/limit.py
hashquery/model/source/match_steps.py
hashquery/model/source/pick.py
hashquery/model/source/sort.py
hashquery/model/source/source.py
hashquery/model/source/sql_text.py
hashquery/model/source/table_name.py
hashquery/model/source/union.py
hashquery/run/__init__.py
hashquery/run/run.py
hashquery/run/run_results.py
hashquery-0.3.0.dist-info/LICENSE
hashquery-0.3.0.dist-info/METADATA
hashquery-0.3.0.dist-info/WHEEL
hashquery-0.3.0.dist-info/top_level.txt
hashquery-0.3.0.dist-info/RECORD
